djangocms_git_md_page-2.0.1.dist-info/licenses/LICENSE
git_md_page/__init__.py
git_md_page/cms_plugins.py
git_md_page/urls.py
git_md_page/views.py
git_md_page/admin/__init__.py
git_md_page/admin/git_plugin.py
git_md_page/forms/__init__.py
git_md_page/forms/git_plugins.py
git_md_page/locale/cs/LC_MESSAGES/django.mo
git_md_page/locale/cs/LC_MESSAGES/django.po
git_md_page/migrations/0001_initial.py
git_md_page/migrations/0002_gitrepository_branch.py
git_md_page/migrations/0003_unique_url.py
git_md_page/migrations/__init__.py
git_md_page/models/__init__.py
git_md_page/models/git_plugins.py
git_md_page/signals/__init__.py
git_md_page/signals/git_update.py
git_md_page/templates/git_md_page/git_text.html
djangocms_git_md_page-2.0.1.dist-info/METADATA
djangocms_git_md_page-2.0.1.dist-info/WHEEL
djangocms_git_md_page-2.0.1.dist-info/top_level.txt
djangocms_git_md_page-2.0.1.dist-info/RECORD
