Metadata-Version: 2.4
Name: djangocms-git-md-page
Version: 2.0.1
Home-page: https://github.com/CZ-NIC/djangocms-git-md-page
Author: CZ.NIC, z.s.p.o.
Author-email: kontakt@nic.cz
Classifier: Framework :: Django CMS :: 3.11
Classifier: Framework :: Django CMS :: 4.1
Classifier: Programming Language :: Python :: 3.9
Classifier: Programming Language :: Python :: 3.10
Classifier: Programming Language :: Python :: 3.11
Classifier: Programming Language :: Python :: 3.12
License-File: LICENSE
Requires-Dist: django-cms>=3.11
Requires-Dist: gitpython~=3.1
Requires-Dist: markdown~=3.5
Provides-Extra: quality
Requires-Dist: black; extra == "quality"
Requires-Dist: flake8; extra == "quality"
Requires-Dist: isort; extra == "quality"
Requires-Dist: mypy; extra == "quality"
Requires-Dist: polint; extra == "quality"
Requires-Dist: pydocstyle; extra == "quality"
Dynamic: license-file
